CHANGELOG.md
hexital/__init__.py
hexital/analysis/__init__.py
hexital/analysis/movement.py
hexital/analysis/patterns.py
hexital/analysis/utils.py
hexital/candlesticks/__init__.py
hexital/candlesticks/heikinashi.py
hexital/core/__init__.py
hexital/core/candle.py
hexital/core/candle_manager.py
hexital/core/candlestick_type.py
hexital/core/hexital.py
hexital/core/indicator.py
hexital/core/indicator_collection.py
hexital/exceptions.py
hexital/indicators/__init__.py
hexital/indicators/adx.py
hexital/indicators/amorph.py
hexital/indicators/aroon.py
hexital/indicators/atr.py
hexital/indicators/bbands.py
hexital/indicators/cmo.py
hexital/indicators/counter.py
hexital/indicators/donchian.py
hexital/indicators/ema.py
hexital/indicators/highest_lowest.py
hexital/indicators/hla.py
hexital/indicators/hlca.py
hexital/indicators/hma.py
hexital/indicators/jma.py
hexital/indicators/kc.py
hexital/indicators/macd.py
hexital/indicators/mfi.py
hexital/indicators/midpoint.py
hexital/indicators/obv.py
hexital/indicators/pivot_points.py
hexital/indicators/rma.py
hexital/indicators/roc.py
hexital/indicators/rsi.py
hexital/indicators/rvi.py
hexital/indicators/sma.py
hexital/indicators/stdev.py
hexital/indicators/stdevthres.py
hexital/indicators/stoch.py
hexital/indicators/supertrend.py
hexital/indicators/tr.py
hexital/indicators/tsi.py
hexital/indicators/vwap.py
hexital/indicators/vwma.py
hexital/indicators/wma.py
hexital/utils/__init__.py
hexital/utils/candles.py
hexital/utils/candlesticks.py
hexital/utils/common.py
hexital/utils/indexing.py
hexital/utils/timeframe.py
hexital/utils/weakreflist.py
hexital-3.0.1.dist-info/LICENSE
hexital-3.0.1.dist-info/METADATA
hexital-3.0.1.dist-info/WHEEL
hexital-3.0.1.dist-info/RECORD
