Metadata-Version: 2.1
Name: hexital
Version: 3.0.1
Summary: Hex Incremental Technical Analysis Library
Home-page: https://github.com/MerlinR/Hexital
License: MIT
Keywords: trading,quant,indicators
Author: Merlin Roe
Author-email: merlin.roe@hotmail.co.uk
Requires-Python: >=3.10,<4.0
Classifier: Development Status :: 4 - Beta
Classifier: Intended Audience :: Developers
Classifier: Intended Audience :: Financial and Insurance Industry
Classifier: Intended Audience :: Science/Research
Classifier: License :: OSI Approved :: MIT License
Classifier: Programming Language :: Python :: 3
Classifier: Programming Language :: Python :: 3.10
Classifier: Programming Language :: Python :: 3.11
Classifier: Topic :: Software Development :: Build Tools
Classifier: Topic :: Software Development :: Libraries :: Python Modules
Classifier: Typing :: Typed
Project-URL: Documentation, https://github.com/MerlinR/Hexital
Project-URL: Repository, https://github.com/MerlinR/Hexital
